loglan_core/__init__.py
loglan_core/author.py
loglan_core/base.py
loglan_core/connect_tables.py
loglan_core/definition.py
loglan_core/event.py
loglan_core/key.py
loglan_core/setting.py
loglan_core/syllable.py
loglan_core/table_names.py
loglan_core/type.py
loglan_core/word.py
loglan_core/word_spell.py
loglan_core/addons/__init__.py
loglan_core/addons/base_selector.py
loglan_core/addons/definition_selector.py
loglan_core/addons/export_word_converter.py
loglan_core/addons/exporter.py
loglan_core/addons/key_selector.py
loglan_core/addons/utils.py
loglan_core/addons/word_linker.py
loglan_core/addons/word_selector.py
loglan_core/addons/word_sourcer.py
Loglan_Core-0.5.0.dist-info/LICENSE
Loglan_Core-0.5.0.dist-info/METADATA
Loglan_Core-0.5.0.dist-info/WHEEL
Loglan_Core-0.5.0.dist-info/top_level.txt
Loglan_Core-0.5.0.dist-info/RECORD
