Metadata-Version: 2.1
Name: Loglan-Core
Version: 0.5.0
Summary: Loglan Dictionary Database Model for SQLAlchemy
Author-email: torrua <torrua@gmail.com>
License: MIT
Project-URL: Download, https://github.com/torrua/loglan_core/archive/0.5.0.tar.gz
Project-URL: Homepage, https://github.com/torrua/loglan_core
Project-URL: Repository, https://github.com/torrua/loglan_core
Keywords: Loglan,Dictionary,Database,Model,LOD
Classifier: Development Status :: 5 - Production/Stable
Classifier: Intended Audience :: Developers
Classifier: Intended Audience :: Science/Research
Classifier: Topic :: Database
Classifier: License :: OSI Approved :: MIT License
Classifier: Programming Language :: Python :: 3.10
Classifier: Programming Language :: Python :: 3.11
Classifier: Programming Language :: Python :: 3.12
Requires-Python: >=3.10
License-File: LICENSE
Requires-Dist: sqlalchemy[asyncio] >=2.0.21
